pyACA/FeatureSpectralCentroid.py
pyACA/FeatureSpectralCrestFactor.py
pyACA/FeatureSpectralDecrease.py
pyACA/FeatureSpectralFlatness.py
pyACA/FeatureSpectralFlux.py
pyACA/FeatureSpectralKurtosis.py
pyACA/FeatureSpectralMfccs.py
pyACA/FeatureSpectralPitchChroma.py
pyACA/FeatureSpectralRolloff.py
pyACA/FeatureSpectralSkewness.py
pyACA/FeatureSpectralSlope.py
pyACA/FeatureSpectralSpread.py
pyACA/FeatureSpectralTonalPowerRatio.py
pyACA/FeatureTimeAcfCoeff.py
pyACA/FeatureTimeMaxAcf.py
pyACA/FeatureTimePeakEnvelope.py
pyACA/FeatureTimeRms.py
pyACA/FeatureTimeStd.py
pyACA/FeatureTimeZeroCrossingRate.py
pyACA/NoveltyFlux.py
pyACA/NoveltyHainsworth.py
pyACA/NoveltyLaroche.py
pyACA/PitchSpectralAcf.py
pyACA/PitchSpectralHps.py
pyACA/PitchTimeAcf.py
pyACA/PitchTimeAmdf.py
pyACA/PitchTimeAuditory.py
pyACA/PitchTimeZeroCrossings.py
pyACA/ToolBin2Freq.py
pyACA/ToolBlockAudio.py
pyACA/ToolComputeHann.py
pyACA/ToolDownmix.py
pyACA/ToolFreq2Bark.py
pyACA/ToolFreq2Bin.py
pyACA/ToolFreq2Mel.py
pyACA/ToolFreq2Midi.py
pyACA/ToolGammatoneFb.py
pyACA/ToolGmm.py
pyACA/ToolInstFreq.py
pyACA/ToolLooCrossVal.py
pyACA/ToolMel2Freq.py
pyACA/ToolMfccFb.py
pyACA/ToolMidi2Freq.py
pyACA/ToolNormalizeAudio.py
pyACA/ToolPca.py
pyACA/ToolPreprocAudio.py
pyACA/ToolReadAudio.py
pyACA/ToolResample.py
pyACA/ToolSeqFeatureSel.py
pyACA/ToolSimpleDtw.py
pyACA/ToolSimpleKmeans.py
pyACA/ToolSimpleKnn.py
pyACA/ToolSimpleNmf.py
pyACA/ToolViterbi.py
pyACA/__init__.py
pyACA/computeBeatHisto.py
pyACA/computeChords.py
pyACA/computeFeature.py
pyACA/computeFingerprint.py
pyACA/computeKey.py
pyACA/computeMelSpectrogram.py
pyACA/computeNoveltyFunction.py
pyACA/computePitch.py
pyACA/computeSpectrogram.py
pyACA/getFeatureList.py
pyACA-0.3.1.dist-info/LICENSE
pyACA-0.3.1.dist-info/METADATA
pyACA-0.3.1.dist-info/WHEEL
pyACA-0.3.1.dist-info/top_level.txt
pyACA-0.3.1.dist-info/RECORD
