Metadata-Version: 2.1
Name: pyACA
Version: 0.3.1
Summary: scripts accompanying the book An Introduction to Audio Content Analysis by Alexander Lerch
Home-page: https://github.com/alexanderlerch/pyACA
Author: Alexander Lerch
Author-email: info@AudioContentAnalysis.org
License: MIT
Keywords: audio analysis features pitch key extraction music onset beat detection descriptors
Platform: UNKNOWN
Classifier: Development Status :: 3 - Alpha
Classifier: License :: OSI Approved :: MIT License
Classifier: Programming Language :: Python :: 3
Classifier: Topic :: Multimedia :: Sound/Audio :: Analysis
License-File: LICENSE
